README.md
setup.py
libpythonproap/__init__.py
libpythonproap/github_api.py
libpythonproap.egg-info/PKG-INFO
libpythonproap.egg-info/SOURCES.txt
libpythonproap.egg-info/dependency_links.txt
libpythonproap.egg-info/not-zip-safe
libpythonproap.egg-info/requires.txt
libpythonproap.egg-info/top_level.txt